satkit_data/__init__.py
satkit_data/data/EGM96.gfc
satkit_data/data/EOP-All.csv
satkit_data/data/ITU_GRACE16.gfc
satkit_data/data/JGM2.gfc
satkit_data/data/JGM3.gfc
satkit_data/data/SW-All.csv
satkit_data/data/leap-seconds.list
satkit_data/data/linux_p1550p2650.440
satkit_data/data/tab5.2a.txt
satkit_data/data/tab5.2b.txt
satkit_data/data/tab5.2d.txt
satkit_data-0.8.0.dist-info/METADATA
satkit_data-0.8.0.dist-info/WHEEL
satkit_data-0.8.0.dist-info/top_level.txt
satkit_data-0.8.0.dist-info/RECORD
