Metadata-Version: 2.4
Name: satkit-data
Version: 0.8.0
Summary: Datafiles for the Satellite Orbital Dynamics Toolkit, Updated Nov 9 2025
Author-email: Steven Michael <ssmichael@gmail.com>
Maintainer-email: Steven Michael <ssmichael@gmail.com>
Keywords: satellite,orbit,astrodynamics,SGP4,TLE,JPL,Ephemeris
